post_instruct/__init__.py
post_instruct/collator.py
post_instruct/datasets.py
post_instruct/model.py
post_instruct/training.py
post_instruct-0.1.1.dist-info/LICENSE
post_instruct-0.1.1.dist-info/METADATA
post_instruct-0.1.1.dist-info/WHEEL
post_instruct-0.1.1.dist-info/RECORD
